README.txt
setup.cfg
setup.py
as/__init__.py
as.recipe.filetemplate.egg-info/PKG-INFO
as.recipe.filetemplate.egg-info/SOURCES.txt
as.recipe.filetemplate.egg-info/dependency_links.txt
as.recipe.filetemplate.egg-info/entry_points.txt
as.recipe.filetemplate.egg-info/namespace_packages.txt
as.recipe.filetemplate.egg-info/requires.txt
as.recipe.filetemplate.egg-info/top_level.txt
as.recipe.filetemplate.egg-info/zip-safe
as/recipe/__init__.py
as/recipe/filetemplate/__init__.py
as/recipe/filetemplate/tests.py