Metadata-Version: 1.1
Name: as.recipe.filetemplate
Version: 2.2.0
Summary: zc.buildout recipe for creating files from file templates
Home-page: http://pypi.python.org/pypi/as.recipe.filetemplate
Author: Gary Poster
Author-email: gary.poster@canonical.com
License: ZPL 2.1
Platform: UNKNOWN
Classifier: Development Status :: 5 - Production/Stable
Classifier: Intended Audience :: Developers
Classifier: License :: OSI Approved :: Zope Public License
Classifier: Programming Language :: Python
Classifier: Operating System :: OS Independent
Classifier: Topic :: Software Development :: Build Tools
Classifier: Framework :: Buildout
